pyibs/__init__.py
pyibs/ibs.py
pyibs/ibs_basic.py
pyibs/ibs_example_1_basic_use.ipynb
pyibs/ibs_example_2_parameter_estimation.ipynb
pyibs/ibs_simple_example.ipynb
pyibs/psycho_generator.py
pyibs/psycho_neg_logl.py
PyIBS-0.1.0.dist-info/LICENSE
PyIBS-0.1.0.dist-info/METADATA
PyIBS-0.1.0.dist-info/WHEEL
PyIBS-0.1.0.dist-info/top_level.txt
PyIBS-0.1.0.dist-info/RECORD
